setup.py
PepipostAPIV10Lib/APIException.py
PepipostAPIV10Lib/APIHelper.py
PepipostAPIV10Lib/Configuration.py
PepipostAPIV10Lib/Decorators.py
PepipostAPIV10Lib/PepipostAPIV10Client.py
PepipostAPIV10Lib/__init__.py
PepipostAPIV10Lib.egg-info/PKG-INFO
PepipostAPIV10Lib.egg-info/SOURCES.txt
PepipostAPIV10Lib.egg-info/dependency_links.txt
PepipostAPIV10Lib.egg-info/not-zip-safe
PepipostAPIV10Lib.egg-info/top_level.txt