Metadata-Version: 1.0
Name: PepipostAPIV10Lib
Version: 0.1
Summary: Official repository of the Pepipost SDK for Python
Home-page: https://github.com/pepipost/pepipost-sdk-python
Author: Tabrez Shaikh
Author-email: tabrez@pepipost.com
License: MIT
Platform: UNKNOWN
